magen_gmail_client-0.0.1.dist-info/DESCRIPTION.rst
magen_gmail_client-0.0.1.dist-info/METADATA
magen_gmail_client-0.0.1.dist-info/RECORD
magen_gmail_client-0.0.1.dist-info/WHEEL
magen_gmail_client-0.0.1.dist-info/metadata.json
magen_gmail_client-0.0.1.dist-info/top_level.txt
magen_gmail_client_api/__init__.py
magen_gmail_client_api/gmail_client.py
